eepromino/__init__.py
eepromino/cli.py
eepromino-0.1.4.dist-info/COPYING
eepromino-0.1.4.dist-info/METADATA
eepromino-0.1.4.dist-info/WHEEL
eepromino-0.1.4.dist-info/entry_points.txt
eepromino-0.1.4.dist-info/top_level.txt
eepromino-0.1.4.dist-info/RECORD
